{"BOP":{"value":0.4982},"AD":{"value":-155205268.1237},"OBV":{"value":4280949209},"HT_TRENDMODE":{"value":1},"SAR":{"value":826.3572},"TRANGE":{"value":28},"STOCHF":{"value":86.8075},"STOCH":{"value":84.1565},"SMA":{"value":916.06},"EMA":{"value":929.5864},"WMA":{"value":940.8809},"TRIMA":{"value":914.8183},"WILLR":{"value":-8.4081},"CCI":{"value":86.8267},"MINUS_DM":{"value":66.3568},"PLUS_DM":{"value":136.6638},"BBANDS":{"value":1016.2142},"MIDPOINT":{"value":916.95},"MIDPRICE":{"value":921.45},"ADOSC":{"value":5471971.3673},"KAMA":{"value":944.1266},"RSI":{"value":69.5939},"MOM":{"value":123},"CMO":{"value":39.1878},"ROC":{"value":14.4028},"ROCR":{"value":1.144},"AROON":{"value":80},"AROONOSC":{"value":70},"MFI":{"value":75.6371},"DX":{"value":34.6305},"MINUS_DI":{"value":18.2259},"PLUS_DI":{"value":37.5368},"ATR":{"value":36.4079},"NATR":{"value":3.674},"STOCHRSI":{"value":66.0589},"DEMA":{"value":965.8883},"ADX":{"value":30.0854},"APO":{"value":15.4474},"PPO":{"value":1.74},"TEMA":{"value":988.8588},"ADXR":{"value":27.8328},"TRIX":{"value":0.3378},"ULTOSC":{"value":67.5547},"MAMA":{"value":1064.7226},"HT_DCPERIOD":{"value":25.0253},"HT_PHASOR":{"value":27.3765},"MACD":{"value":19.134},"MACDEXT":{"value":32.5451},"T3":{"value":887.3517},"HT_TRENDLINE":{"value":882.7775},"HT_SINE":{"value":0.5268},"HT_DCPHASE":{"value":103.2129}}